pokereval/__init__.py
pokereval/card.py
pokereval/hand_evaluator.py
pokereval/lookup_tables.py
pokereval/popcount.py
pokereval/tests.py
pokereval-0.2.0.dist-info/LICENSE.txt
pokereval-0.2.0.dist-info/METADATA
pokereval-0.2.0.dist-info/WHEEL
pokereval-0.2.0.dist-info/top_level.txt
pokereval-0.2.0.dist-info/RECORD
