Metadata-Version: 2.1
Name: pokereval
Version: 0.2.0
Summary: A pure python poker hand evaluator for 5, 6, 7 cards
Home-page: https://github.com/aliang/pokerhand-eval
Author: Alvin Liang
Author-email: ayliang@gmail.com
License: Apache, see LICENSE.txt
Platform: UNKNOWN
